sk_dsp_comm/sdr_helper/__init__.py
sk_dsp_comm/sdr_helper/__version__.py
sk_dsp_comm/sdr_helper/rtlsdr.py
sk_dsp_comm/sdr_helper/sdr_helper.py
sk_dsp_comm/sdr_helper/test/__init__.py
sk_dsp_comm/sdr_helper/test/test_imports.py
sdr_helper-1.0.1.dist-info/LICENSE
sdr_helper-1.0.1.dist-info/METADATA
sdr_helper-1.0.1.dist-info/WHEEL
sdr_helper-1.0.1.dist-info/top_level.txt
sdr_helper-1.0.1.dist-info/RECORD
