Metadata-Version: 2.1
Name: sdr-helper
Version: 1.0.1
Summary: SDR Helper
Home-page: https://github.com/scikit-dsp-comm/sdr_helper
Author: Mark Wickert
Author-email: mwickert@uccs.edu
Maintainer: Chiranth Siddappa
Maintainer-email: chiranthsiddappa@gmail.com
License: BSD
Platform: UNKNOWN
Requires-Python: >=3.5
Requires-Dist: colorama
Requires-Dist: scikit-dsp-comm
Requires-Dist: numpy
Requires-Dist: scipy
Requires-Dist: pyaudio
Requires-Dist: pyaudio-helper
Requires-Dist: setuptools (>=40.1.0)
Provides-Extra: rtlsdr
Requires-Dist: pyrtlsdr ; extra == 'rtlsdr'
